pytest_selenium_pdiff/__init__.py
pytest_selenium_pdiff/assertions.py
pytest_selenium_pdiff/exceptions.py
pytest_selenium_pdiff/pytest_selenium_pdiff.py
pytest_selenium_pdiff/utils.py
pytest_selenium_pdiff-0.4.0.dist-info/DESCRIPTION.rst
pytest_selenium_pdiff-0.4.0.dist-info/entry_points.txt
pytest_selenium_pdiff-0.4.0.dist-info/METADATA
pytest_selenium_pdiff-0.4.0.dist-info/metadata.json
pytest_selenium_pdiff-0.4.0.dist-info/RECORD
pytest_selenium_pdiff-0.4.0.dist-info/top_level.txt
pytest_selenium_pdiff-0.4.0.dist-info/WHEEL
