Metadata-Version: 2.0
Name: pytest-selenium-pdiff
Version: 0.4.0
Summary: A pytest package implementing perceptualdiff for Selenium tests.
Home-page: https://github.com/rentlytics/pytest-selenium-pdiff
Author: Phil Plante
Author-email: phil@rentlytics.com
License: MIT
Keywords: pytest selenium pdiff perceptualdiff
Platform: UNKNOWN
Classifier: Development Status :: 2 - Pre-Alpha
Classifier: Intended Audience :: Developers
Classifier: License :: OSI Approved :: ISC License (ISCL)
Classifier: Natural Language :: English
Classifier: Programming Language :: Python :: 2
Classifier: Programming Language :: Python :: 2.6
Classifier: Programming Language :: Python :: 2.7
Classifier: Programming Language :: Python :: 3
Classifier: Programming Language :: Python :: 3.3
Classifier: Programming Language :: Python :: 3.4
Classifier: Programming Language :: Python :: 3.5
Classifier: Framework :: Pytest
Requires-Dist: pytest (>=2.9.2)
Requires-Dist: pytest-selenium (>=1.3.1)
Requires-Dist: sh (==1.11)
Requires-Dist: pillow (==4.0.0)
